<?xml version="1.0" encoding="UTF-8"?>
<objects serializationModel="Studio.02.03.00">
	<object class="AudioFile" id="{cb2e54d0-1dfb-47e6-857a-4c5fd6163cf1}">
		<property name="assetPath">
			<value>Sound Assets/FootstepsGrass_16.wav</value>
		</property>
		<property name="frequencyInKHz">
			<value>192</value>
		</property>
		<property name="channelCount">
			<value>2</value>
		</property>
		<property name="length">
			<value>0.69335416666666672</value>
		</property>
		<relationship name="masterAssetFolder">
			<destination>{87141b2c-14ae-4bd0-b17b-6338c22d2609}</destination>
		</relationship>
	</object>
</objects>
